pretalx_pages/__init__.py
pretalx_pages/apps.py
pretalx_pages/models.py
pretalx_pages/signals.py
pretalx_pages/urls.py
pretalx_pages/views.py
pretalx_pages/locale/django.pot
pretalx_pages/locale/ar/LC_MESSAGES/django.mo
pretalx_pages/locale/ar/LC_MESSAGES/django.po
pretalx_pages/locale/bg/LC_MESSAGES/django.mo
pretalx_pages/locale/bg/LC_MESSAGES/django.po
pretalx_pages/locale/ca/LC_MESSAGES/django.mo
pretalx_pages/locale/ca/LC_MESSAGES/django.po
pretalx_pages/locale/cs/LC_MESSAGES/django.mo
pretalx_pages/locale/cs/LC_MESSAGES/django.po
pretalx_pages/locale/de_DE/LC_MESSAGES/django.mo
pretalx_pages/locale/de_DE/LC_MESSAGES/django.po
pretalx_pages/locale/de_Formal/LC_MESSAGES/django.mo
pretalx_pages/locale/de_Formal/LC_MESSAGES/django.po
pretalx_pages/locale/el/LC_MESSAGES/django.mo
pretalx_pages/locale/el/LC_MESSAGES/django.po
pretalx_pages/locale/en_Mozilla/LC_MESSAGES/django.mo
pretalx_pages/locale/es/LC_MESSAGES/django.mo
pretalx_pages/locale/es/LC_MESSAGES/django.po
pretalx_pages/locale/es_MX/LC_MESSAGES/django.mo
pretalx_pages/locale/es_MX/LC_MESSAGES/django.po
pretalx_pages/locale/fr_FR/LC_MESSAGES/django.mo
pretalx_pages/locale/fr_FR/LC_MESSAGES/django.po
pretalx_pages/locale/id/LC_MESSAGES/django.mo
pretalx_pages/locale/id/LC_MESSAGES/django.po
pretalx_pages/locale/it/LC_MESSAGES/django.mo
pretalx_pages/locale/it/LC_MESSAGES/django.po
pretalx_pages/locale/ja_JP/LC_MESSAGES/django.mo
pretalx_pages/locale/ja_JP/LC_MESSAGES/django.po
pretalx_pages/locale/ko/LC_MESSAGES/django.mo
pretalx_pages/locale/ko/LC_MESSAGES/django.po
pretalx_pages/locale/nl/LC_MESSAGES/django.mo
pretalx_pages/locale/nl/LC_MESSAGES/django.po
pretalx_pages/locale/pl/LC_MESSAGES/django.mo
pretalx_pages/locale/pl/LC_MESSAGES/django.po
pretalx_pages/locale/pt_BR/LC_MESSAGES/django.mo
pretalx_pages/locale/pt_BR/LC_MESSAGES/django.po
pretalx_pages/locale/pt_PT/LC_MESSAGES/django.mo
pretalx_pages/locale/pt_PT/LC_MESSAGES/django.po
pretalx_pages/locale/ru/LC_MESSAGES/django.mo
pretalx_pages-1.7.0.dist-info/licenses/LICENSE
pretalx_pages-1.7.0.dist-info/METADATA
pretalx_pages-1.7.0.dist-info/WHEEL
pretalx_pages-1.7.0.dist-info/entry_points.txt
pretalx_pages-1.7.0.dist-info/top_level.txt
pretalx_pages-1.7.0.dist-info/RECORD
