Metadata-Version: 2.4
Name: pretalx-pages
Version: 1.7.0
Summary: Static pages for pretalx, e.g. information, venue listings, a Code of Conduct, etc.
Author-email: Tobias Kunze <r@rixx.de>
Maintainer-email: Tobias Kunze <r@rixx.de>
License: Apache Software License
Project-URL: homepage, https://github.com/pretalx/pretalx-pages
Project-URL: repository, https://github.com/pretalx/pretalx-pages.git
Keywords: pretalx
License-File: LICENSE
Dynamic: license-file
